bricco/__init__.py
bricco/main.py
bricco-1.0.2.dist-info/METADATA
bricco-1.0.2.dist-info/WHEEL
bricco-1.0.2.dist-info/entry_points.txt
bricco-1.0.2.dist-info/licenses/LICENSE
bricco-1.0.2.dist-info/RECORD
