Metadata-Version: 2.3
Name: bricco
Version: 1.0.2
Summary: A simple Tor bridges testing tool
Project-URL: Repository, https://codeberg.org/screwery/bricco
Project-URL: Issues, https://codeberg.org/screwery/bricco/issues
Project-URL: Changelog, https://codeberg.org/screwery/bricco/src/branch/main/CHANGELOG.md
Author-email: Ellie Viesná <snowboard_refinery@proton.me>
License-Expression: GPL-3.0-or-later
License-File: LICENSE
Keywords: bridge,censorship,obfs4,tor
Classifier: Development Status :: 4 - Beta
Classifier: Environment :: Console
Classifier: License :: OSI Approved :: GNU General Public License v3 (GPLv3)
Classifier: Natural Language :: English
Classifier: Operating System :: OS Independent
Classifier: Programming Language :: Python :: 3.11
Requires-Python: >=3.11
